qiskit_addon_aqc_tensor/__init__.py
qiskit_addon_aqc_tensor/objective.py
qiskit_addon_aqc_tensor/ansatz_generation/__init__.py
qiskit_addon_aqc_tensor/ansatz_generation/from_connectivity.py
qiskit_addon_aqc_tensor/ansatz_generation/parametrize_circuit.py
qiskit_addon_aqc_tensor/simulation/__init__.py
qiskit_addon_aqc_tensor/simulation/abstract.py
qiskit_addon_aqc_tensor/simulation/explicit_gradient.py
qiskit_addon_aqc_tensor/simulation/aer/__init__.py
qiskit_addon_aqc_tensor/simulation/aer/gradient.py
qiskit_addon_aqc_tensor/simulation/aer/simulation.py
qiskit_addon_aqc_tensor/simulation/aer/state.py
qiskit_addon_aqc_tensor/simulation/quimb/__init__.py
qiskit_addon_aqc_tensor-0.2.0.dist-info/METADATA
qiskit_addon_aqc_tensor-0.2.0.dist-info/WHEEL
qiskit_addon_aqc_tensor-0.2.0.dist-info/licenses/LICENSE.txt
qiskit_addon_aqc_tensor-0.2.0.dist-info/RECORD
