Metadata-Version: 2.4
Name: qiskit-addon-aqc-tensor
Version: 0.2.0
Summary: Approximate quantum compilation with tensor networks
Project-URL: Documentation, https://qiskit.github.io/qiskit-addon-aqc-tensor/
Project-URL: Repository, https://github.com/Qiskit/qiskit-addon-aqc-tensor
License:                     Copyright 2024 IBM and its contributors
License-File: LICENSE.txt
Classifier: Intended Audience :: Developers
Classifier: Intended Audience :: Science/Research
Classifier: License :: OSI Approved :: Apache Software License
Classifier: Natural Language :: English
Classifier: Operating System :: MacOS
Classifier: Operating System :: Microsoft :: Windows
Classifier: Operating System :: POSIX :: Linux
Classifier: Programming Language :: Python :: 3.9
Classifier: Programming Language :: Python :: 3.10
Classifier: Programming Language :: Python :: 3.11
Classifier: Programming Language :: Python :: 3.12
Classifier: Programming Language :: Python :: 3.13
Classifier: Topic :: Scientific/Engineering :: Physics
Requires-Python: >=3.9
Requires-Dist: numpy>=1.23.0
Requires-Dist: plum-dispatch>=2.4.1
Requires-Dist: qiskit<3,>=1.3.0
Requires-Dist: scipy>=1.11.0
Requires-Dist: wrapt>=1.13.3
Provides-Extra: aer
Requires-Dist: qiskit-aer>=0.14.2; extra == 'aer'
Provides-Extra: basetest
Requires-Dist: pytest-randomly>=1.2.0; extra == 'basetest'
Requires-Dist: pytest>=7.0.0; extra == 'basetest'
Provides-Extra: dev
Requires-Dist: autoflake==2.3.1; extra == 'dev'
Requires-Dist: black[jupyter]~=25.1; extra == 'dev'
Requires-Dist: mypy==1.15.0; extra == 'dev'
Requires-Dist: nbmake>=1.4.3; extra == 'dev'
Requires-Dist: nbqa>=1.6.0; extra == 'dev'
Requires-Dist: pylint==3.3.4; extra == 'dev'
Requires-Dist: pytest-randomly>=1.2.0; extra == 'dev'
Requires-Dist: pytest-subtests>=0.11.0; extra == 'dev'
Requires-Dist: pytest>=7.0.0; extra == 'dev'
Requires-Dist: qiskit-addon-utils>=0.1.0; extra == 'dev'
Requires-Dist: reno>=3.4.0; extra == 'dev'
Requires-Dist: ruff==0.9.9; extra == 'dev'
Provides-Extra: docs
Requires-Dist: jupyter-sphinx>=0.3.2; extra == 'docs'
Requires-Dist: nbsphinx>=0.8.8; extra == 'docs'
Requires-Dist: qiskit-sphinx-theme~=2.0.0; extra == 'docs'
Requires-Dist: reno>=3.4.0; extra == 'docs'
Requires-Dist: sphinx-autodoc-typehints>=1.12.0; extra == 'docs'
Requires-Dist: sphinx-copybutton>=0.5.0; extra == 'docs'
Requires-Dist: sphinx-reredirects; extra == 'docs'
Requires-Dist: sphinx>=3.0.0; extra == 'docs'
Provides-Extra: lint
Requires-Dist: autoflake==2.3.1; extra == 'lint'
Requires-Dist: black[jupyter]~=25.1; extra == 'lint'
Requires-Dist: mypy==1.15.0; extra == 'lint'
Requires-Dist: nbqa>=1.6.0; extra == 'lint'
Requires-Dist: pylint==3.3.4; extra == 'lint'
Requires-Dist: reno>=3.4.0; extra == 'lint'
Requires-Dist: ruff==0.9.9; extra == 'lint'
Provides-Extra: nbtest
Requires-Dist: nbmake>=1.4.3; extra == 'nbtest'
Requires-Dist: pytest-randomly>=1.2.0; extra == 'nbtest'
Requires-Dist: pytest>=7.0.0; extra == 'nbtest'
Provides-Extra: notebook-dependencies
Requires-Dist: ipywidgets>=7.5.1; extra == 'notebook-dependencies'
Requires-Dist: jax>=0.4.30; extra == 'notebook-dependencies'
Requires-Dist: kahypar>=1.3.5; ((sys_platform == 'linux' or sys_platform == 'darwin') and python_version < '3.14') and extra == 'notebook-dependencies'
Requires-Dist: matplotlib>=3.3.4; extra == 'notebook-dependencies'
Requires-Dist: networkx>=2.3; (python_version < '3.14') and extra == 'notebook-dependencies'
Requires-Dist: pylatexenc>=2.0; extra == 'notebook-dependencies'
Requires-Dist: qiskit-addon-utils>=0.1.0; extra == 'notebook-dependencies'
Requires-Dist: qiskit-aer>=0.14.2; extra == 'notebook-dependencies'
Requires-Dist: qiskit-ibm-runtime>=0.24.0; extra == 'notebook-dependencies'
Requires-Dist: qiskit-quimb<0.1,>=0.0.4; (python_version < '3.14') and extra == 'notebook-dependencies'
Requires-Dist: quimb<2,>=1.8.4; (python_version < '3.14') and extra == 'notebook-dependencies'
Provides-Extra: quimb
Requires-Dist: kahypar>=1.3.5; ((sys_platform == 'linux' or sys_platform == 'darwin') and python_version < '3.14') and extra == 'quimb'
Requires-Dist: networkx>=2.3; (python_version < '3.14') and extra == 'quimb'
Requires-Dist: qiskit-quimb<0.1,>=0.0.4; (python_version < '3.14') and extra == 'quimb'
Requires-Dist: quimb<2,>=1.8.4; (python_version < '3.14') and extra == 'quimb'
Provides-Extra: quimb-all
Requires-Dist: autograd>=1.7.0; extra == 'quimb-all'
Requires-Dist: jax>=0.4.30; extra == 'quimb-all'
Requires-Dist: kahypar>=1.3.5; ((sys_platform == 'linux' or sys_platform == 'darwin') and python_version < '3.14') and extra == 'quimb-all'
Requires-Dist: networkx>=2.3; (python_version < '3.14') and extra == 'quimb-all'
Requires-Dist: qiskit-quimb<0.1,>=0.0.4; (python_version < '3.14') and extra == 'quimb-all'
Requires-Dist: quimb<2,>=1.8.4; (python_version < '3.14') and extra == 'quimb-all'
Provides-Extra: quimb-autograd
Requires-Dist: autograd>=1.7.0; extra == 'quimb-autograd'
Requires-Dist: kahypar>=1.3.5; ((sys_platform == 'linux' or sys_platform == 'darwin') and python_version < '3.14') and extra == 'quimb-autograd'
Requires-Dist: networkx>=2.3; (python_version < '3.14') and extra == 'quimb-autograd'
Requires-Dist: qiskit-quimb<0.1,>=0.0.4; (python_version < '3.14') and extra == 'quimb-autograd'
Requires-Dist: quimb<2,>=1.8.4; (python_version < '3.14') and extra == 'quimb-autograd'
Provides-Extra: quimb-jax
Requires-Dist: jax>=0.4.30; extra == 'quimb-jax'
Requires-Dist: kahypar>=1.3.5; ((sys_platform == 'linux' or sys_platform == 'darwin') and python_version < '3.14') and extra == 'quimb-jax'
Requires-Dist: networkx>=2.3; (python_version < '3.14') and extra == 'quimb-jax'
Requires-Dist: qiskit-quimb<0.1,>=0.0.4; (python_version < '3.14') and extra == 'quimb-jax'
Requires-Dist: quimb<2,>=1.8.4; (python_version < '3.14') and extra == 'quimb-jax'
Provides-Extra: style
Requires-Dist: autoflake==2.3.1; extra == 'style'
Requires-Dist: black[jupyter]~=25.1; extra == 'style'
Requires-Dist: nbqa>=1.6.0; extra == 'style'
Requires-Dist: ruff==0.9.9; extra == 'style'
Provides-Extra: test
Requires-Dist: pytest-randomly>=1.2.0; extra == 'test'
Requires-Dist: pytest-subtests>=0.11.0; extra == 'test'
Requires-Dist: pytest>=7.0.0; extra == 'test'
Requires-Dist: qiskit-addon-utils>=0.1.0; extra == 'test'
